eqip
