Metadata-Version: 2.1
Name: eqip
Version: 0.5.0
Summary: EM Quasi-Isotropic Prediction
Home-page: https://github.com/hanslovsky/eqip
Author: Philipp Hanslovsky
Author-email: hanslovskyp@janelia.hhmi.org
License: UNKNOWN
Platform: UNKNOWN
Requires-Python: >=3.6
